steer/drive/__init__.py
steer/drive/headers.py
steer/drive/upload.py
steer/oauth/__init__.py
steer/oauth/api.py
steer/oauth/challenge.py
steer/oauth/response.py
steer-1.2.0.dist-info/LICENSE
steer-1.2.0.dist-info/METADATA
steer-1.2.0.dist-info/WHEEL
steer-1.2.0.dist-info/top_level.txt
steer-1.2.0.dist-info/RECORD
