Metadata-Version: 2.1
Name: steer
Version: 1.2.0
Summary: Create URLS to use create google oauth2 and drive api requests.
Home-page: https://github.com/fernando-gap/steer
Author: Fernando A.
License: MIT
Platform: UNKNOWN
License-File: LICENSE
